omie_py/__about__.py
omie_py/__init__.py
omie_py/client.py
omie_py/py.typed
omie_py-0.0.0.dist-info/METADATA
omie_py-0.0.0.dist-info/WHEEL
omie_py-0.0.0.dist-info/licenses/LICENSE
omie_py-0.0.0.dist-info/RECORD
