Metadata-Version: 2.3
Name: omie-py
Version: 0.0.0
Summary: Client não oficial da Omie API em Python
Project-URL: homepage, https://github.com/buserbrasil/omie-py
Project-URL: repository, https://github.com/buserbrasil/omie-py
Author-email: Murillo Bianconi <murillo.bianconi@buser.com.br>
License-File: LICENSE
Keywords: api,client,omie,python
Classifier: Development Status :: 3 - Alpha
Classifier: Intended Audience :: Developers
Classifier: License :: OSI Approved :: MIT License
Classifier: Programming Language :: Python :: 3.11
Classifier: Topic :: Software Development :: Libraries :: Python Modules
Requires-Python: >=3.11
Requires-Dist: zeep>=4.3.1
